{
    "semester": "23L",
    "103A-INxxx-ISP-SKPS": {
        "LABORATORIUM": [
          "Zapoznanie z Buildroot (BR)",
          "Zapoznanie z OpenWRT",
          "Kontynuacja OpenWRT",
          "Wieloprocesowe przetwarzanie danych",
          "Projekt cz. 1",
          "Projekt cz. 2"
        ],
        "WYKLAD": [
          "Wprowadzenie (Winiarski)",
          "Środowiska do zastosowań wbudowanych i sterowania (Zabołotny)",
          "Zaawansowane użycie BR, Wprowadzenie do OpenWRT (Zabołotny)",
          "Realizacja komunikacji między procesowej (Zabołotny)",
          "QEMU, Komunikacja z urządzeniami I/O (Zabołotny)",
          "Techniki przystowania Linuxa do czasu rzeczywistego (Zabołotny)",
          "Kolokwium nr 1",
          "SoC i MPSoC (Zabołotny)",
          "Sprzęt z naciskiem na sterowniki (Winiarski)",
          "Organizacja oprogramowania bez systemu operacyjnego (Winiarski)",
          "Przykładowy system z mikrokontrolerem (Winiarski)",
          "Szeregowanie zadań i aspekty bezpieczeństwa (Winiarski)",
          "Sieci przemysłowe (Winiarski)",
          "Kolokwium nr 2",
          "Kolokwium poprawkowe"
        ]
    },
    "103A-INxxx-ISP-SWO": {
        "LABORATORIUM": [
          "Edytor, Git, Rewizja kodu (Wysota)",
          "Środowisko, Potok CI/CD, testy (Grochowski)",
          "Monitorowanie, debuggowanie, profilowanie (Chwesiuk)",
          "Praca z kodem zastanym, refaktoring (Radlak)"
        ],
        "WYKLAD": [
          "Organizacja, podstawy (Nowak)",
          "Styl kodowania (Grochowski)",
          "Wzorce projektowe 1 (Nowak)",
          "Wzorce projektowe 2 (Nowak), Git (Wysota)",
          "UML (Grochowski)",
          "Cykl wytwarzania oprogramowania 1 (Grochowski)",
          "Cykl wytwarzania oprogramowania 2 (Grochowski)",
          "Ocena jakości kodu i testów (Grochowski)",
          "Kolokwium nr 1, Wzorce projektowe 3 (Nowak)",
          "Monitorowanie i analiza aplikacji (Grochowski)",
          "Refaktoring i praca z kodem zastanym (Grochowski)",
          "Współbieżne wzorce projektowe 1 (Nowak)",
          "Współbieżne wzorce projektowe 2 (Nowak)",
          "Kolokwium nr 2",
          "Zasowy internetowe i standardy (Nowak)"
        ]
    },
    "103A-INxxx-ISP-WSYZ": {
        "LABORATORIUM": [
          "Procesy biznesowe - BPMN",
          "Narzędzia do modelowania i optymalizacji",
          "Metody harmonogramowania zadań",
          "Metody planowania produkcji i usług"
        ],
        "WYKLAD": [
          "Organizacja, systemy informacyjne",
          "Architektury systemów i inne aspekty 1",
          "Architektury systemów i inne aspekty 2",
          "Modelowanie procesów biznesowych",
          "Przegląd modeli analitycznych",
          "Wybrane modele optymalizacyjne 1",
          "Wybrane modele optymalizacyjne 2",
          "Kolokwium nr 1",
          "Harmonogramowanie i szeregowanie zadań 1",
          "Harmonogramowanie i szeregowanie zadań 2",
          "Planowanie produkcji i usług",
          "Metody zarządzania dystrybucją i lokalizacją",
          "Systemy ERP z przykładami",
          "Systemy Business Intelligence i Big Data",
          "Kolokwium nr 2"
        ]
    },
    "103A-INxxx-ISP-WMM": {
        "LABORATORIUM": {
          "default": [
            "Analiza widmowa sygnałów dyskretnych (lab1)",
            "Filtracja obrazu cyfrowego (lab4)",
            "Statystyczne właściwości obrazów (lab5)",
            "Strumieniowanie danych multimedialnych (lab6)",
            "Sygnał mowy (lab2)",
            "Śledzenie obrazów (lab7)",
            "Filtracja, efekty dźwiękowe (lab3)",
            "Grafika komputerowa (lab8)"
          ],
          "104": [
            "Analiza widmowa sygnałów dyskretnych (lab1)",
            "Filtracja obrazu cyfrowego (lab4)",
            "Statystyczne właściwości obrazów (lab5)",
            "Sygnał mowy (lab2)",
            "Strumieniowanie danych multimedialnych (lab6)",
            "Śledzenie obrazów (lab7)",
            "Filtracja, efekty dźwiękowe (lab3)",
            "Grafika komputerowa (lab8)"
          ]
        },
        "WYKLAD": [
          "SGN Organizacja i wprowadzenie do sygnałów",
          "SGN Szereg i przekształcenie Fouriera",
          "SGN Próbkowanie i kwantyzacja",
          "SGN Przetwarzanie sygnałów cyfrowych",
          "SGN Filtracja cyfrowa",
          "Podstawy teorii informacji",
          "WZJ Podstawy techniki obrazowej",
          "WZJ Przetwarzanie obrazów",
          "WZJ Kompresja obrazów",
          "WZJ Kompresja wideo",
          "WZJ Strumieniowanie",
          "WZJ Analiza wizyjna",
          "WZJ Indeksowanie",
          "DZWK Sygnały akustyczne",
          "DZWK Lokalizacja źródła, jakość dźwięku",
          "DZWK Cyfrowe sygnały foniczne",
          "DZWK Synteza mowy",
          "DZWK Filtracja, synteza, kompresja",
          "DZWK Dźwięk przestrzenny",
          "DZWK",
          "GRFK Reprezentacje obiektów i przekształcenia",
          "GRFK",
          "GRFK Eliminacja powierzchni, cieniowanie"
        ]
    },
    "103B-INxxx-ISP-BSS": {
        "LABORATORIUM": [
          "Algorytmy szyfrowania",
          "OpenSSL",
          "Stunnel",
          "GPG",
          "Systemy IDS",
          "Bezpieczeństwo aplikacji",
          "Bezpieczeństwo aplikacji WWW"
        ],
        "WYKLAD": [
          "Wprowadzenie",
          "Szyfry",
          "Funkcje skrótu",
          "PKI",
          "Zagrożenia sieciowe",
          "Systemy bezpieczeństwa",
          "Bezpieczeństwo aplikacji C/C++",
          "Malware 1",
          "Malware 2",
          "Aplikacje webowe",
          "Systemy operacyjne i VPN",
          "Systemy ICS",
          "Systemy HoneyPot",
          "Polityka bezpieczeństwa"
        ]
    }
}
